{
    "uniqueId": "page-15d684e7-9c00-4679-9840-c918e4bc2d31",
    "title": "Press Releases",
    "language": "en",
    "created": 1760945741,
    "modified": 1763537741,
    "layout": {
        "columns": 1,
        "rows": [
            {
                "columns": 1,
                "backgroundColor": "var(--color-primary-element)",
                "widgets": [
                    {
                        "type": "image",
                        "column": 1,
                        "order": 1,
                        "src": "news-media.jpg",
                        "alt": "Press releases",
                        "objectFit": "cover"
                    },
                    {
                        "type": "heading",
                        "column": 1,
                        "order": 2,
                        "content": "Press Releases",
                        "level": 1
                    },
                    {
                        "type": "text",
                        "column": 1,
                        "order": 3,
                        "content": "Official press releases and media resources"
                    }
                ]
            },
            {
                "columns": 1,
                "backgroundColor": "",
                "widgets": [
                    {
                        "type": "heading",
                        "column": 1,
                        "order": 1,
                        "content": "Latest Press Releases",
                        "level": 2
                    },
                    {
                        "type": "text",
                        "column": 1,
                        "order": 2,
                        "content": "**IntraVox Announces Version 1.0** - November 2025\n\nIntraVox, the open-source intranet platform for Nextcloud, today announced the release of version 1.0, marking a major milestone in bringing enterprise-grade content management to the Nextcloud ecosystem."
                    }
                ]
            },
            {
                "columns": 1,
                "backgroundColor": "var(--color-background-hover)",
                "widgets": [
                    {
                        "type": "heading",
                        "column": 1,
                        "order": 1,
                        "content": "Media Kit",
                        "level": 2
                    },
                    {
                        "type": "text",
                        "column": 1,
                        "order": 2,
                        "content": "Download our press kit including logos, screenshots, and brand guidelines."
                    },
                    {
                        "type": "links",
                        "column": 1,
                        "order": 3,
                        "columns": 2,
                        "items": [
                            {
                                "title": "Download Press Kit",
                                "text": "Logos, screenshots, and media assets",
                                "url": "#",
                                "icon": "download",
                                "target": "_blank"
                            },
                            {
                                "title": "Brand Guidelines",
                                "text": "Official brand usage and style guide",
                                "url": "#",
                                "icon": "palette",
                                "target": "_blank"
                            }
                        ]
                    }
                ]
            }
        ]
    }
}